django_cdn/__init__.py
django_cdn/apps.py
django_cdn/package_manager.py
django_cdn-1.0.0.dist-info/LICENSE
django_cdn-1.0.0.dist-info/METADATA
django_cdn-1.0.0.dist-info/WHEEL
django_cdn-1.0.0.dist-info/top_level.txt
django_cdn-1.0.0.dist-info/RECORD
