Metadata-Version: 2.1
Name: django-cdn
Version: 1.0.0
Summary: Django library that simplifies HTML imports of JS and CSS code with a NPM like command.
Home-page: https://github.com/Casassarnau/django-cdn
Author: Arnau Casas Saez
Author-email: casassarnau@gmail.com
License: MIT
Project-URL: Bug Tracker, https://github.com/Casassarnau/django-cdn/issues
Classifier: Development Status :: 5 - Production/Stable
Classifier: Framework :: Django
Classifier: Framework :: Django :: 4.2
Classifier: Framework :: Django :: 4.1
Classifier: Framework :: Django :: 4.0
Classifier: Framework :: Django :: 3.2
Classifier: Framework :: Django :: 3.1
Classifier: Framework :: Django :: 3.0
Classifier: Intended Audience :: Developers
Classifier: License :: OSI Approved :: MIT License
Classifier: Programming Language :: Python :: 3
Classifier: Programming Language :: Python :: 3.11
Classifier: Programming Language :: Python :: 3.10
Classifier: Programming Language :: Python :: 3.9
Classifier: Programming Language :: Python :: 3.8
Classifier: Programming Language :: Python :: 3.7
Classifier: Topic :: Software Development :: Libraries :: Python Modules
Requires-Python: >=3.6
License-File: LICENSE
Requires-Dist: django >=2.2
Requires-Dist: semver
Requires-Dist: requests
